Metadata-Version: 2.1
Name: scaner3dphoto
Version: 1.0.3
Summary: 3d scanner via photo using transformers library (GLPN models)
Home-page: https://github.com/diglukhikh/scaner
Author: d.i.glukhikh
Author-email: gluhihdmitry@gmail.ru
License: GNU General Public License v3.0
Platform: UNKNOWN
Classifier: License :: OSI Approved :: Apache Software License
Classifier: Operating System :: OS Independent
Classifier: Intended Audience :: End Users/Desktop
Classifier: Intended Audience :: Developers
Classifier: Programming Language :: Python
Classifier: Programming Language :: Python :: 3
Classifier: Programming Language :: Python :: 3.8
Classifier: Programming Language :: Python :: 3.9
Classifier: Programming Language :: Python :: Implementation :: PyPy
Classifier: Programming Language :: Python :: Implementation :: CPython
